{
 "map": "NarakaCity",
 "extent": 3000,
 "terrain_pos": [
  -3000.0,
  0.0,
  -3000.0
 ],
 "terrain_size": [
  6000.0,
  500.0,
  6000.0
 ],
 "resources": [
  {
   "idx": 0,
   "name": "ResourceArea_Balterium",
   "type": "Balterium",
   "active": false,
   "x": -102.6,
   "y": 185.5,
   "z": -2956.6,
   "grid_w": 9,
   "grid_h": 9,
   "cell_size": 13.0,
   "world_w": 117.0,
   "world_h": 117.0,
   "resources_current": 0,
   "resources_max": 0
  },
  {
   "idx": 1,
   "name": "ResourceArea_Balterium",
   "type": "Balterium",
   "active": false,
   "x": -773.9,
   "y": 215.3,
   "z": -2225.1,
   "grid_w": 11,
   "grid_h": 10,
   "cell_size": 13.0,
   "world_w": 143.0,
   "world_h": 130.0,
   "resources_current": 0,
   "resources_max": 0
  },
  {
   "idx": 2,
   "name": "ResourceArea_Balterium",
   "type": "Balterium",
   "active": false,
   "x": -2274.2,
   "y": 285.0,
   "z": 1876.0,
   "grid_w": 9,
   "grid_h": 11,
   "cell_size": 13.0,
   "world_w": 117.0,
   "world_h": 143.0,
   "resources_current": 0,
   "resources_max": 0
  },
  {
   "idx": 3,
   "name": "ResourceArea_Balterium",
   "type": "Balterium",
   "active": false,
   "x": -876.2,
   "y": 186.0,
   "z": 2273.5,
   "grid_w": 8,
   "grid_h": 9,
   "cell_size": 13.0,
   "world_w": 104.0,
   "world_h": 117.0,
   "resources_current": 0,
   "resources_max": 0
  },
  {
   "idx": 4,
   "name": "ResourceArea_Balterium",
   "type": "Balterium",
   "active": false,
   "x": 2517.0,
   "y": 386.9,
   "z": -2664.4,
   "grid_w": 11,
   "grid_h": 11,
   "cell_size": 13.0,
   "world_w": 143.0,
   "world_h": 143.0,
   "resources_current": 0,
   "resources_max": 0
  },
  {
   "idx": 5,
   "name": "ResourceArea_Balterium",
   "type": "Balterium",
   "active": false,
   "x": 2604.9,
   "y": 396.6,
   "z": 153.4,
   "grid_w": 11,
   "grid_h": 9,
   "cell_size": 13.0,
   "world_w": 143.0,
   "world_h": 117.0,
   "resources_current": 0,
   "resources_max": 0
  },
  {
   "idx": 6,
   "name": "ResourceArea_Balterium",
   "type": "Balterium",
   "active": false,
   "x": 2011.0,
   "y": 313.3,
   "z": -1411.6,
   "grid_w": 9,
   "grid_h": 9,
   "cell_size": 13.0,
   "world_w": 117.0,
   "world_h": 117.0,
   "resources_current": 0,
   "resources_max": 0
  },
  {
   "idx": 7,
   "name": "ResourceArea_Balterium",
   "type": "Balterium",
   "active": false,
   "x": -2693.7,
   "y": 174.5,
   "z": -131.4,
   "grid_w": 9,
   "grid_h": 11,
   "cell_size": 13.0,
   "world_w": 117.0,
   "world_h": 143.0,
   "resources_current": 0,
   "resources_max": 0
  },
  {
   "idx": 8,
   "name": "ResourceArea_Balterium",
   "type": "Balterium",
   "active": false,
   "x": -524.3,
   "y": 20.8,
   "z": 867.7,
   "grid_w": 9,
   "grid_h": 9,
   "cell_size": 13.0,
   "world_w": 117.0,
   "world_h": 117.0,
   "resources_current": 0,
   "resources_max": 0
  },
  {
   "idx": 9,
   "name": "ResourceArea_Balterium",
   "type": "Balterium",
   "active": false,
   "x": -961.7,
   "y": 222.0,
   "z": -2701.0,
   "grid_w": 12,
   "grid_h": 12,
   "cell_size": 13.0,
   "world_w": 156.0,
   "world_h": 156.0,
   "resources_current": 0,
   "resources_max": 0
  },
  {
   "idx": 10,
   "name": "ResourceArea_Balterium",
   "type": "Balterium",
   "active": false,
   "x": 318.5,
   "y": 46.8,
   "z": 820.9,
   "grid_w": 9,
   "grid_h": 9,
   "cell_size": 13.0,
   "world_w": 117.0,
   "world_h": 117.0,
   "resources_current": 0,
   "resources_max": 0
  },
  {
   "idx": 11,
   "name": "ResourceArea_Balterium",
   "type": "Balterium",
   "active": false,
   "x": -262.7,
   "y": 175.0,
   "z": -2370.2,
   "grid_w": 9,
   "grid_h": 11,
   "cell_size": 13.0,
   "world_w": 117.0,
   "world_h": 143.0,
   "resources_current": 0,
   "resources_max": 0
  },
  {
   "idx": 12,
   "name": "ResourceArea_Balterium",
   "type": "Balterium",
   "active": false,
   "x": -2868.4,
   "y": 66.7,
   "z": -924.3,
   "grid_w": 9,
   "grid_h": 12,
   "cell_size": 13.0,
   "world_w": 117.0,
   "world_h": 156.0,
   "resources_current": 0,
   "resources_max": 0
  },
  {
   "idx": 13,
   "name": "ResourceArea_Balterium",
   "type": "Balterium",
   "active": false,
   "x": 423.1,
   "y": 90.1,
   "z": -2949.5,
   "grid_w": 9,
   "grid_h": 8,
   "cell_size": 13.0,
   "world_w": 117.0,
   "world_h": 104.0,
   "resources_current": 0,
   "resources_max": 0
  },
  {
   "idx": 14,
   "name": "ResourceArea_Balterium",
   "type": "Balterium",
   "active": false,
   "x": 1841.8,
   "y": 291.8,
   "z": -2551.7,
   "grid_w": 9,
   "grid_h": 11,
   "cell_size": 13.0,
   "world_w": 117.0,
   "world_h": 143.0,
   "resources_current": 0,
   "resources_max": 0
  },
  {
   "idx": 15,
   "name": "ResourceArea_Balterium",
   "type": "Balterium",
   "active": false,
   "x": -1993.9,
   "y": 272.3,
   "z": 1608.1,
   "grid_w": 9,
   "grid_h": 11,
   "cell_size": 13.0,
   "world_w": 117.0,
   "world_h": 143.0,
   "resources_current": 0,
   "resources_max": 0
  },
  {
   "idx": 16,
   "name": "ResourceArea_Balterium",
   "type": "Balterium",
   "active": false,
   "x": 1270.5,
   "y": 398.9,
   "z": 1837.0,
   "grid_w": 13,
   "grid_h": 9,
   "cell_size": 13.0,
   "world_w": 169.0,
   "world_h": 117.0,
   "resources_current": 0,
   "resources_max": 0
  },
  {
   "idx": 17,
   "name": "ResourceArea_Balterium",
   "type": "Balterium",
   "active": false,
   "x": 1816.1,
   "y": 396.7,
   "z": 900.5,
   "grid_w": 9,
   "grid_h": 12,
   "cell_size": 13.0,
   "world_w": 117.0,
   "world_h": 156.0,
   "resources_current": 0,
   "resources_max": 0
  },
  {
   "idx": 18,
   "name": "ResourceArea_Balterium",
   "type": "Balterium",
   "active": false,
   "x": 1862.6,
   "y": 392.1,
   "z": 290.5,
   "grid_w": 8,
   "grid_h": 12,
   "cell_size": 13.0,
   "world_w": 104.0,
   "world_h": 156.0,
   "resources_current": 0,
   "resources_max": 0
  },
  {
   "idx": 19,
   "name": "ResourceArea_Balterium",
   "type": "Balterium",
   "active": false,
   "x": 353.0,
   "y": 200.7,
   "z": 2843.6,
   "grid_w": 9,
   "grid_h": 11,
   "cell_size": 13.0,
   "world_w": 117.0,
   "world_h": 143.0,
   "resources_current": 0,
   "resources_max": 0
  },
  {
   "idx": 20,
   "name": "ResourceArea_Balterium",
   "type": "Balterium",
   "active": false,
   "x": -941.4,
   "y": 35.4,
   "z": -797.3,
   "grid_w": 9,
   "grid_h": 9,
   "cell_size": 13.0,
   "world_w": 117.0,
   "world_h": 117.0,
   "resources_current": 0,
   "resources_max": 0
  },
  {
   "idx": 21,
   "name": "ResourceArea_Balterium",
   "type": "Balterium",
   "active": false,
   "x": -2657.1,
   "y": 209.0,
   "z": 300.5,
   "grid_w": 9,
   "grid_h": 11,
   "cell_size": 13.0,
   "world_w": 117.0,
   "world_h": 143.0,
   "resources_current": 0,
   "resources_max": 0
  },
  {
   "idx": 22,
   "name": "ResourceArea_Balterium",
   "type": "Balterium",
   "active": false,
   "x": 860.8,
   "y": 77.1,
   "z": -2884.9,
   "grid_w": 9,
   "grid_h": 9,
   "cell_size": 13.0,
   "world_w": 117.0,
   "world_h": 117.0,
   "resources_current": 0,
   "resources_max": 0
  },
  {
   "idx": 23,
   "name": "ResourceArea_Balterium",
   "type": "Balterium",
   "active": false,
   "x": -1618.9,
   "y": 260.9,
   "z": 2240.6,
   "grid_w": 12,
   "grid_h": 11,
   "cell_size": 13.0,
   "world_w": 156.0,
   "world_h": 143.0,
   "resources_current": 0,
   "resources_max": 0
  },
  {
   "idx": 24,
   "name": "ResourceArea_Balterium",
   "type": "Balterium",
   "active": false,
   "x": -559.6,
   "y": 87.8,
   "z": 2955.2,
   "grid_w": 9,
   "grid_h": 10,
   "cell_size": 13.0,
   "world_w": 117.0,
   "world_h": 130.0,
   "resources_current": 0,
   "resources_max": 0
  },
  {
   "idx": 25,
   "name": "ResourceArea_Balterium",
   "type": "Balterium",
   "active": false,
   "x": 2587.0,
   "y": 386.8,
   "z": -357.4,
   "grid_w": 10,
   "grid_h": 11,
   "cell_size": 13.0,
   "world_w": 130.0,
   "world_h": 143.0,
   "resources_current": 0,
   "resources_max": 0
  },
  {
   "idx": 26,
   "name": "ResourceArea_Balterium",
   "type": "Balterium",
   "active": false,
   "x": 356.5,
   "y": 55.9,
   "z": 1515.0,
   "grid_w": 10,
   "grid_h": 11,
   "cell_size": 13.0,
   "world_w": 130.0,
   "world_h": 143.0,
   "resources_current": 0,
   "resources_max": 0
  },
  {
   "idx": 27,
   "name": "ResourceArea_Balterium",
   "type": "Balterium",
   "active": false,
   "x": -2242.0,
   "y": 32.3,
   "z": -1194.0,
   "grid_w": 10,
   "grid_h": 8,
   "cell_size": 13.0,
   "world_w": 130.0,
   "world_h": 104.0,
   "resources_current": 0,
   "resources_max": 0
  },
  {
   "idx": 28,
   "name": "ResourceArea_Balterium",
   "type": "Balterium",
   "active": false,
   "x": 556.5,
   "y": 50.4,
   "z": -1350.7,
   "grid_w": 9,
   "grid_h": 9,
   "cell_size": 13.0,
   "world_w": 117.0,
   "world_h": 117.0,
   "resources_current": 0,
   "resources_max": 0
  },
  {
   "idx": 29,
   "name": "ResourceArea_Balterium",
   "type": "Balterium",
   "active": false,
   "x": 1429.1,
   "y": 451.4,
   "z": 1417.0,
   "grid_w": 10,
   "grid_h": 13,
   "cell_size": 13.0,
   "world_w": 130.0,
   "world_h": 169.0,
   "resources_current": 0,
   "resources_max": 0
  },
  {
   "idx": 30,
   "name": "ResourceArea_Balterium",
   "type": "Balterium",
   "active": false,
   "x": 2748.2,
   "y": 479.8,
   "z": 2619.6,
   "grid_w": 9,
   "grid_h": 12,
   "cell_size": 13.0,
   "world_w": 117.0,
   "world_h": 156.0,
   "resources_current": 0,
   "resources_max": 0
  },
  {
   "idx": 31,
   "name": "ResourceArea_Balterium",
   "type": "Balterium",
   "active": false,
   "x": 1956.1,
   "y": 471.7,
   "z": 2618.5,
   "grid_w": 9,
   "grid_h": 9,
   "cell_size": 13.0,
   "world_w": 117.0,
   "world_h": 117.0,
   "resources_current": 0,
   "resources_max": 0
  },
  {
   "idx": 32,
   "name": "ResourceArea_Balterium",
   "type": "Balterium",
   "active": false,
   "x": -1970.6,
   "y": 249.5,
   "z": -2770.2,
   "grid_w": 9,
   "grid_h": 9,
   "cell_size": 13.0,
   "world_w": 117.0,
   "world_h": 117.0,
   "resources_current": 0,
   "resources_max": 0
  },
  {
   "idx": 33,
   "name": "ResourceArea_Balterium",
   "type": "Balterium",
   "active": false,
   "x": -1359.5,
   "y": 206.3,
   "z": 604.2,
   "grid_w": 11,
   "grid_h": 10,
   "cell_size": 13.0,
   "world_w": 143.0,
   "world_h": 130.0,
   "resources_current": 0,
   "resources_max": 0
  },
  {
   "idx": 34,
   "name": "ResourceArea_Balterium",
   "type": "Balterium",
   "active": false,
   "x": -860.3,
   "y": 27.3,
   "z": -315.7,
   "grid_w": 9,
   "grid_h": 9,
   "cell_size": 13.0,
   "world_w": 117.0,
   "world_h": 117.0,
   "resources_current": 0,
   "resources_max": 0
  },
  {
   "idx": 35,
   "name": "ResourceArea_Balterium",
   "type": "Balterium",
   "active": false,
   "x": 1846.4,
   "y": 347.8,
   "z": -305.0,
   "grid_w": 10,
   "grid_h": 10,
   "cell_size": 13.0,
   "world_w": 130.0,
   "world_h": 130.0,
   "resources_current": 0,
   "resources_max": 0
  },
  {
   "idx": 36,
   "name": "ResourceArea_Balterium",
   "type": "Balterium",
   "active": false,
   "x": 414.0,
   "y": 59.6,
   "z": -928.0,
   "grid_w": 10,
   "grid_h": 11,
   "cell_size": 13.0,
   "world_w": 130.0,
   "world_h": 143.0,
   "resources_current": 0,
   "resources_max": 0
  },
  {
   "idx": 37,
   "name": "ResourceArea_Balterium",
   "type": "Balterium",
   "active": false,
   "x": 2655.7,
   "y": 482.3,
   "z": 1548.1,
   "grid_w": 10,
   "grid_h": 11,
   "cell_size": 13.0,
   "world_w": 130.0,
   "world_h": 143.0,
   "resources_current": 0,
   "resources_max": 0
  },
  {
   "idx": 38,
   "name": "ResourceArea_Balterium",
   "type": "Balterium",
   "active": false,
   "x": -1863.8,
   "y": 62.2,
   "z": -796.4,
   "grid_w": 10,
   "grid_h": 11,
   "cell_size": 13.0,
   "world_w": 130.0,
   "world_h": 143.0,
   "resources_current": 0,
   "resources_max": 0
  },
  {
   "idx": 39,
   "name": "ResourceArea_Balterium",
   "type": "Balterium",
   "active": false,
   "x": -2869.7,
   "y": 181.9,
   "z": -2152.9,
   "grid_w": 9,
   "grid_h": 10,
   "cell_size": 13.0,
   "world_w": 117.0,
   "world_h": 130.0,
   "resources_current": 0,
   "resources_max": 0
  },
  {
   "idx": 40,
   "name": "ResourceArea_Balterium",
   "type": "Balterium",
   "active": false,
   "x": 808.6,
   "y": 49.5,
   "z": 873.1,
   "grid_w": 10,
   "grid_h": 10,
   "cell_size": 13.0,
   "world_w": 130.0,
   "world_h": 130.0,
   "resources_current": 0,
   "resources_max": 0
  },
  {
   "idx": 41,
   "name": "ResourceArea_Balterium",
   "type": "Balterium",
   "active": false,
   "x": -112.5,
   "y": 88.0,
   "z": 2927.8,
   "grid_w": 11,
   "grid_h": 11,
   "cell_size": 13.0,
   "world_w": 143.0,
   "world_h": 143.0,
   "resources_current": 0,
   "resources_max": 0
  },
  {
   "idx": 42,
   "name": "ResourceArea_Balterium",
   "type": "Balterium",
   "active": false,
   "x": -464.3,
   "y": 26.2,
   "z": 1356.1,
   "grid_w": 9,
   "grid_h": 10,
   "cell_size": 13.0,
   "world_w": 117.0,
   "world_h": 130.0,
   "resources_current": 0,
   "resources_max": 0
  },
  {
   "idx": 43,
   "name": "ResourceArea_Balterium",
   "type": "Balterium",
   "active": false,
   "x": 1358.5,
   "y": 48.7,
   "z": -667.4,
   "grid_w": 9,
   "grid_h": 9,
   "cell_size": 13.0,
   "world_w": 117.0,
   "world_h": 117.0,
   "resources_current": 0,
   "resources_max": 0
  },
  {
   "idx": 44,
   "name": "ResourceArea_Balterium",
   "type": "Balterium",
   "active": false,
   "x": -2128.4,
   "y": 231.7,
   "z": 607.3,
   "grid_w": 10,
   "grid_h": 11,
   "cell_size": 13.0,
   "world_w": 130.0,
   "world_h": 143.0,
   "resources_current": 0,
   "resources_max": 0
  },
  {
   "idx": 45,
   "name": "ResourceArea_Balterium",
   "type": "Balterium",
   "active": false,
   "x": 1266.1,
   "y": 245.1,
   "z": 568.3,
   "grid_w": 10,
   "grid_h": 10,
   "cell_size": 13.0,
   "world_w": 130.0,
   "world_h": 130.0,
   "resources_current": 0,
   "resources_max": 0
  },
  {
   "idx": 46,
   "name": "ResourceArea_Balterium",
   "type": "Balterium",
   "active": false,
   "x": -2271.2,
   "y": 70.2,
   "z": -765.7,
   "grid_w": 9,
   "grid_h": 11,
   "cell_size": 13.0,
   "world_w": 117.0,
   "world_h": 143.0,
   "resources_current": 0,
   "resources_max": 0
  },
  {
   "idx": 47,
   "name": "ResourceArea_Balterium",
   "type": "Balterium",
   "active": false,
   "x": -1572.4,
   "y": 39.9,
   "z": -1206.9,
   "grid_w": 9,
   "grid_h": 10,
   "cell_size": 13.0,
   "world_w": 117.0,
   "world_h": 130.0,
   "resources_current": 0,
   "resources_max": 0
  },
  {
   "idx": 48,
   "name": "ResourceArea_Balterium",
   "type": "Balterium",
   "active": false,
   "x": -1263.0,
   "y": 273.1,
   "z": 1942.3,
   "grid_w": 9,
   "grid_h": 10,
   "cell_size": 13.0,
   "world_w": 117.0,
   "world_h": 130.0,
   "resources_current": 0,
   "resources_max": 0
  },
  {
   "idx": 49,
   "name": "ResourceArea_Balterium",
   "type": "Balterium",
   "active": false,
   "x": -1389.2,
   "y": 245.8,
   "z": 1385.6,
   "grid_w": 8,
   "grid_h": 9,
   "cell_size": 13.0,
   "world_w": 104.0,
   "world_h": 117.0,
   "resources_current": 0,
   "resources_max": 0
  },
  {
   "idx": 50,
   "name": "ResourceArea_Balterium",
   "type": "Balterium",
   "active": false,
   "x": -1666.8,
   "y": 200.6,
   "z": 103.2,
   "grid_w": 9,
   "grid_h": 10,
   "cell_size": 13.0,
   "world_w": 117.0,
   "world_h": 130.0,
   "resources_current": 0,
   "resources_max": 0
  },
  {
   "idx": 51,
   "name": "ResourceArea_Balterium",
   "type": "Balterium",
   "active": false,
   "x": -2544.3,
   "y": 205.1,
   "z": -2811.3,
   "grid_w": 10,
   "grid_h": 9,
   "cell_size": 13.0,
   "world_w": 130.0,
   "world_h": 117.0,
   "resources_current": 0,
   "resources_max": 0
  },
  {
   "idx": 52,
   "name": "ResourceArea_Balterium",
   "type": "Balterium",
   "active": false,
   "x": -30.0,
   "y": 91.1,
   "z": 2440.2,
   "grid_w": 8,
   "grid_h": 9,
   "cell_size": 13.0,
   "world_w": 104.0,
   "world_h": 117.0,
   "resources_current": 0,
   "resources_max": 0
  },
  {
   "idx": 53,
   "name": "ResourceArea_Balterium",
   "type": "Balterium",
   "active": false,
   "x": 613.8,
   "y": 97.8,
   "z": -2501.4,
   "grid_w": 9,
   "grid_h": 10,
   "cell_size": 13.0,
   "world_w": 117.0,
   "world_h": 130.0,
   "resources_current": 0,
   "resources_max": 0
  },
  {
   "idx": 54,
   "name": "ResourceArea_Balterium",
   "type": "Balterium",
   "active": false,
   "x": 233.0,
   "y": 62.9,
   "z": -2056.8,
   "grid_w": 9,
   "grid_h": 11,
   "cell_size": 13.0,
   "world_w": 117.0,
   "world_h": 143.0,
   "resources_current": 0,
   "resources_max": 0
  },
  {
   "idx": 55,
   "name": "ResourceArea_Balterium",
   "type": "Balterium",
   "active": false,
   "x": -382.3,
   "y": 36.8,
   "z": -37.4,
   "grid_w": 10,
   "grid_h": 9,
   "cell_size": 13.0,
   "world_w": 130.0,
   "world_h": 117.0,
   "resources_current": 0,
   "resources_max": 0
  },
  {
   "idx": 56,
   "name": "ResourceArea_Balterium",
   "type": "Balterium",
   "active": false,
   "x": 2881.3,
   "y": 370.4,
   "z": -1680.4,
   "grid_w": 10,
   "grid_h": 10,
   "cell_size": 13.0,
   "world_w": 130.0,
   "world_h": 130.0,
   "resources_current": 0,
   "resources_max": 0
  },
  {
   "idx": 57,
   "name": "ResourceArea_Balterium",
   "type": "Balterium",
   "active": false,
   "x": -2586.5,
   "y": 247.4,
   "z": 1579.8,
   "grid_w": 10,
   "grid_h": 12,
   "cell_size": 13.0,
   "world_w": 130.0,
   "world_h": 156.0,
   "resources_current": 0,
   "resources_max": 0
  },
  {
   "idx": 58,
   "name": "ResourceArea_Balterium",
   "type": "Balterium",
   "active": false,
   "x": -1902.1,
   "y": 177.3,
   "z": -343.2,
   "grid_w": 9,
   "grid_h": 9,
   "cell_size": 13.0,
   "world_w": 117.0,
   "world_h": 117.0,
   "resources_current": 0,
   "resources_max": 0
  },
  {
   "idx": 59,
   "name": "ResourceArea_Balterium",
   "type": "Balterium",
   "active": false,
   "x": 825.7,
   "y": 61.9,
   "z": -1695.3,
   "grid_w": 10,
   "grid_h": 10,
   "cell_size": 13.0,
   "world_w": 130.0,
   "world_h": 130.0,
   "resources_current": 0,
   "resources_max": 0
  },
  {
   "idx": 60,
   "name": "ResourceArea_Balterium",
   "type": "Balterium",
   "active": false,
   "x": 1181.4,
   "y": 338.0,
   "z": 2907.2,
   "grid_w": 9,
   "grid_h": 11,
   "cell_size": 13.0,
   "world_w": 117.0,
   "world_h": 143.0,
   "resources_current": 0,
   "resources_max": 0
  },
  {
   "idx": 61,
   "name": "ResourceArea_Balterium",
   "type": "Balterium",
   "active": false,
   "x": 397.2,
   "y": 44.0,
   "z": -119.2,
   "grid_w": 9,
   "grid_h": 10,
   "cell_size": 13.0,
   "world_w": 117.0,
   "world_h": 130.0,
   "resources_current": 0,
   "resources_max": 0
  },
  {
   "idx": 62,
   "name": "ResourceArea_Balterium",
   "type": "Balterium",
   "active": false,
   "x": 2563.1,
   "y": 474.4,
   "z": 2003.4,
   "grid_w": 11,
   "grid_h": 13,
   "cell_size": 13.0,
   "world_w": 143.0,
   "world_h": 169.0,
   "resources_current": 0,
   "resources_max": 0
  },
  {
   "idx": 63,
   "name": "ResourceArea_Balterium",
   "type": "Balterium",
   "active": false,
   "x": 1304.1,
   "y": 45.6,
   "z": -1256.9,
   "grid_w": 9,
   "grid_h": 9,
   "cell_size": 13.0,
   "world_w": 117.0,
   "world_h": 117.0,
   "resources_current": 0,
   "resources_max": 0
  },
  {
   "idx": 64,
   "name": "ResourceArea_Balterium",
   "type": "Balterium",
   "active": false,
   "x": -1581.1,
   "y": 244.5,
   "z": -2817.0,
   "grid_w": 10,
   "grid_h": 10,
   "cell_size": 13.0,
   "world_w": 130.0,
   "world_h": 130.0,
   "resources_current": 0,
   "resources_max": 0
  },
  {
   "idx": 65,
   "name": "ResourceArea_Balterium",
   "type": "Balterium",
   "active": false,
   "x": 1893.0,
   "y": 345.3,
   "z": -1894.1,
   "grid_w": 9,
   "grid_h": 10,
   "cell_size": 13.0,
   "world_w": 117.0,
   "world_h": 130.0,
   "resources_current": 0,
   "resources_max": 0
  },
  {
   "idx": 66,
   "name": "ResourceArea_Balterium",
   "type": "Balterium",
   "active": false,
   "x": -2826.5,
   "y": 206.8,
   "z": 979.0,
   "grid_w": 9,
   "grid_h": 12,
   "cell_size": 13.0,
   "world_w": 117.0,
   "world_h": 156.0,
   "resources_current": 0,
   "resources_max": 0
  },
  {
   "idx": 67,
   "name": "ResourceArea_Balterium",
   "type": "Balterium",
   "active": false,
   "x": -861.0,
   "y": 32.3,
   "z": -1464.2,
   "grid_w": 9,
   "grid_h": 9,
   "cell_size": 13.0,
   "world_w": 117.0,
   "world_h": 117.0,
   "resources_current": 0,
   "resources_max": 0
  },
  {
   "idx": 68,
   "name": "ResourceArea_Balterium",
   "type": "Balterium",
   "active": false,
   "x": -1308.4,
   "y": 41.8,
   "z": -784.9,
   "grid_w": 9,
   "grid_h": 9,
   "cell_size": 13.0,
   "world_w": 117.0,
   "world_h": 117.0,
   "resources_current": 0,
   "resources_max": 0
  },
  {
   "idx": 69,
   "name": "ResourceArea_Balterium",
   "type": "Balterium",
   "active": false,
   "x": 761.9,
   "y": 51.7,
   "z": -652.5,
   "grid_w": 9,
   "grid_h": 11,
   "cell_size": 13.0,
   "world_w": 117.0,
   "world_h": 143.0,
   "resources_current": 0,
   "resources_max": 0
  },
  {
   "idx": 70,
   "name": "ResourceArea_Balterium",
   "type": "Balterium",
   "active": false,
   "x": 386.5,
   "y": 183.1,
   "z": 2466.4,
   "grid_w": 9,
   "grid_h": 10,
   "cell_size": 13.0,
   "world_w": 117.0,
   "world_h": 130.0,
   "resources_current": 0,
   "resources_max": 0
  },
  {
   "idx": 71,
   "name": "ResourceArea_Balterium",
   "type": "Balterium",
   "active": false,
   "x": -341.9,
   "y": 25.3,
   "z": 536.5,
   "grid_w": 9,
   "grid_h": 10,
   "cell_size": 13.0,
   "world_w": 117.0,
   "world_h": 130.0,
   "resources_current": 0,
   "resources_max": 0
  },
  {
   "idx": 72,
   "name": "ResourceArea_Balterium",
   "type": "Balterium",
   "active": false,
   "x": -2795.7,
   "y": 271.7,
   "z": 2299.2,
   "grid_w": 9,
   "grid_h": 13,
   "cell_size": 13.0,
   "world_w": 117.0,
   "world_h": 169.0,
   "resources_current": 0,
   "resources_max": 0
  },
  {
   "idx": 73,
   "name": "ResourceArea_Balterium",
   "type": "Balterium",
   "active": false,
   "x": 2532.1,
   "y": 370.1,
   "z": -1986.6,
   "grid_w": 9,
   "grid_h": 10,
   "cell_size": 13.0,
   "world_w": 117.0,
   "world_h": 130.0,
   "resources_current": 0,
   "resources_max": 0
  },
  {
   "idx": 74,
   "name": "ResourceArea_Balterium",
   "type": "Balterium",
   "active": false,
   "x": -2293.1,
   "y": 277.9,
   "z": 2809.5,
   "grid_w": 9,
   "grid_h": 12,
   "cell_size": 13.0,
   "world_w": 117.0,
   "world_h": 156.0,
   "resources_current": 0,
   "resources_max": 0
  },
  {
   "idx": 75,
   "name": "ResourceArea_Balterium",
   "type": "Balterium",
   "active": false,
   "x": 2208.1,
   "y": 355.3,
   "z": -783.3,
   "grid_w": 10,
   "grid_h": 9,
   "cell_size": 13.0,
   "world_w": 130.0,
   "world_h": 117.0,
   "resources_current": 0,
   "resources_max": 0
  },
  {
   "idx": 76,
   "name": "ResourceArea_Balterium",
   "type": "Balterium",
   "active": false,
   "x": 866.0,
   "y": 45.0,
   "z": -106.2,
   "grid_w": 9,
   "grid_h": 10,
   "cell_size": 13.0,
   "world_w": 117.0,
   "world_h": 130.0,
   "resources_current": 0,
   "resources_max": 0
  },
  {
   "idx": 77,
   "name": "ResourceArea_Balterium",
   "type": "Balterium",
   "active": false,
   "x": 449.8,
   "y": 44.8,
   "z": 417.5,
   "grid_w": 10,
   "grid_h": 10,
   "cell_size": 13.0,
   "world_w": 130.0,
   "world_h": 130.0,
   "resources_current": 0,
   "resources_max": 0
  },
  {
   "idx": 78,
   "name": "ResourceArea_Balterium",
   "type": "Balterium",
   "active": false,
   "x": 2833.1,
   "y": 393.7,
   "z": -687.7,
   "grid_w": 11,
   "grid_h": 10,
   "cell_size": 13.0,
   "world_w": 143.0,
   "world_h": 130.0,
   "resources_current": 0,
   "resources_max": 0
  },
  {
   "idx": 79,
   "name": "ResourceArea_Balterium",
   "type": "Balterium",
   "active": false,
   "x": 1834.3,
   "y": 476.3,
   "z": 1987.8,
   "grid_w": 9,
   "grid_h": 11,
   "cell_size": 13.0,
   "world_w": 117.0,
   "world_h": 143.0,
   "resources_current": 0,
   "resources_max": 0
  },
  {
   "idx": 80,
   "name": "ResourceArea_Balterium",
   "type": "Balterium",
   "active": false,
   "x": -1646.6,
   "y": 233.8,
   "z": 963.3,
   "grid_w": 9,
   "grid_h": 12,
   "cell_size": 13.0,
   "world_w": 117.0,
   "world_h": 156.0,
   "resources_current": 0,
   "resources_max": 0
  },
  {
   "idx": 81,
   "name": "ResourceArea_Balterium",
   "type": "Balterium",
   "active": false,
   "x": -2051.9,
   "y": 203.8,
   "z": -1842.8,
   "grid_w": 9,
   "grid_h": 11,
   "cell_size": 13.0,
   "world_w": 117.0,
   "world_h": 143.0,
   "resources_current": 0,
   "resources_max": 0
  },
  {
   "idx": 82,
   "name": "ResourceArea_Balterium",
   "type": "Balterium",
   "active": false,
   "x": 2123.6,
   "y": 462.3,
   "z": 1346.8,
   "grid_w": 10,
   "grid_h": 10,
   "cell_size": 13.0,
   "world_w": 130.0,
   "world_h": 130.0,
   "resources_current": 0,
   "resources_max": 0
  },
  {
   "idx": 83,
   "name": "ResourceArea_Balterium",
   "type": "Balterium",
   "active": false,
   "x": -346.0,
   "y": 10.2,
   "z": 1797.2,
   "grid_w": 9,
   "grid_h": 9,
   "cell_size": 13.0,
   "world_w": 117.0,
   "world_h": 117.0,
   "resources_current": 0,
   "resources_max": 0
  },
  {
   "idx": 84,
   "name": "ResourceArea_Balterium",
   "type": "Balterium",
   "active": false,
   "x": 2632.3,
   "y": 442.6,
   "z": 630.2,
   "grid_w": 9,
   "grid_h": 10,
   "cell_size": 13.0,
   "world_w": 117.0,
   "world_h": 130.0,
   "resources_current": 0,
   "resources_max": 0
  },
  {
   "idx": 85,
   "name": "ResourceArea_Balterium",
   "type": "Balterium",
   "active": false,
   "x": -288.0,
   "y": 28.7,
   "z": -1828.2,
   "grid_w": 8,
   "grid_h": 9,
   "cell_size": 13.0,
   "world_w": 104.0,
   "world_h": 117.0,
   "resources_current": 0,
   "resources_max": 0
  },
  {
   "idx": 86,
   "name": "ResourceArea_Balterium",
   "type": "Balterium",
   "active": false,
   "x": 161.2,
   "y": 75.0,
   "z": 1903.7,
   "grid_w": 10,
   "grid_h": 10,
   "cell_size": 13.0,
   "world_w": 130.0,
   "world_h": 130.0,
   "resources_current": 0,
   "resources_max": 0
  },
  {
   "idx": 87,
   "name": "ResourceArea_Balterium",
   "type": "Balterium",
   "active": false,
   "x": 1127.3,
   "y": 360.4,
   "z": 2348.4,
   "grid_w": 9,
   "grid_h": 10,
   "cell_size": 13.0,
   "world_w": 117.0,
   "world_h": 130.0,
   "resources_current": 0,
   "resources_max": 0
  },
  {
   "idx": 88,
   "name": "ResourceArea_Biotics_TarPit",
   "type": "Biotics",
   "active": false,
   "x": 2612.7,
   "y": 388.2,
   "z": -748.2,
   "grid_w": 1,
   "grid_h": 1,
   "cell_size": 3.0,
   "world_w": 3.0,
   "world_h": 3.0,
   "resources_current": 0,
   "resources_max": 0
  },
  {
   "idx": 89,
   "name": "ResourceArea_Biotics_TarPit",
   "type": "Biotics",
   "active": false,
   "x": -254.6,
   "y": 25.0,
   "z": -1458.8,
   "grid_w": 1,
   "grid_h": 1,
   "cell_size": 3.0,
   "world_w": 3.0,
   "world_h": 3.0,
   "resources_current": 0,
   "resources_max": 0
  },
  {
   "idx": 90,
   "name": "ResourceArea_Biotics_TarPit",
   "type": "Biotics",
   "active": false,
   "x": -219.6,
   "y": 159.2,
   "z": -2658.1,
   "grid_w": 1,
   "grid_h": 1,
   "cell_size": 3.0,
   "world_w": 3.0,
   "world_h": 3.0,
   "resources_current": 0,
   "resources_max": 0
  },
  {
   "idx": 91,
   "name": "ResourceArea_Biotics_TarPit",
   "type": "Biotics",
   "active": false,
   "x": 628.7,
   "y": 84.6,
   "z": -2986.8,
   "grid_w": 1,
   "grid_h": 1,
   "cell_size": 3.0,
   "world_w": 3.0,
   "world_h": 3.0,
   "resources_current": 0,
   "resources_max": 0
  },
  {
   "idx": 92,
   "name": "ResourceArea_Biotics_TarPit",
   "type": "Biotics",
   "active": false,
   "x": 1965.1,
   "y": 474.9,
   "z": 2209.7,
   "grid_w": 1,
   "grid_h": 1,
   "cell_size": 3.0,
   "world_w": 3.0,
   "world_h": 3.0,
   "resources_current": 0,
   "resources_max": 0
  },
  {
   "idx": 93,
   "name": "ResourceArea_Biotics_TarPit",
   "type": "Biotics",
   "active": false,
   "x": -321.0,
   "y": 34.3,
   "z": -684.2,
   "grid_w": 1,
   "grid_h": 1,
   "cell_size": 3.0,
   "world_w": 3.0,
   "world_h": 3.0,
   "resources_current": 0,
   "resources_max": 0
  },
  {
   "idx": 94,
   "name": "ResourceArea_Biotics_TarPit",
   "type": "Biotics",
   "active": false,
   "x": 854.4,
   "y": 66.2,
   "z": -2727.0,
   "grid_w": 1,
   "grid_h": 1,
   "cell_size": 3.0,
   "world_w": 3.0,
   "world_h": 3.0,
   "resources_current": 0,
   "resources_max": 0
  },
  {
   "idx": 95,
   "name": "ResourceArea_Biotics_TarPit",
   "type": "Biotics",
   "active": false,
   "x": -42.9,
   "y": 22.2,
   "z": 241.0,
   "grid_w": 1,
   "grid_h": 1,
   "cell_size": 3.0,
   "world_w": 3.0,
   "world_h": 3.0,
   "resources_current": 0,
   "resources_max": 0
  },
  {
   "idx": 96,
   "name": "ResourceArea_Biotics_TarPit",
   "type": "Biotics",
   "active": false,
   "x": 1576.4,
   "y": 71.5,
   "z": -1232.3,
   "grid_w": 1,
   "grid_h": 1,
   "cell_size": 3.0,
   "world_w": 3.0,
   "world_h": 3.0,
   "resources_current": 0,
   "resources_max": 0
  },
  {
   "idx": 97,
   "name": "ResourceArea_Biotics_TarPit",
   "type": "Biotics",
   "active": false,
   "x": -2.5,
   "y": 45.0,
   "z": 1082.8,
   "grid_w": 1,
   "grid_h": 1,
   "cell_size": 3.0,
   "world_w": 3.0,
   "world_h": 3.0,
   "resources_current": 0,
   "resources_max": 0
  },
  {
   "idx": 98,
   "name": "ResourceArea_Biotics_TarPit",
   "type": "Biotics",
   "active": false,
   "x": 113.4,
   "y": 41.9,
   "z": -762.3,
   "grid_w": 1,
   "grid_h": 1,
   "cell_size": 3.0,
   "world_w": 3.0,
   "world_h": 3.0,
   "resources_current": 0,
   "resources_max": 0
  },
  {
   "idx": 99,
   "name": "ResourceArea_Biotics_TarPit",
   "type": "Biotics",
   "active": false,
   "x": 609.7,
   "y": 43.5,
   "z": 880.5,
   "grid_w": 1,
   "grid_h": 1,
   "cell_size": 3.0,
   "world_w": 3.0,
   "world_h": 3.0,
   "resources_current": 0,
   "resources_max": 0
  },
  {
   "idx": 100,
   "name": "ResourceArea_Biotics_TarPit",
   "type": "Biotics",
   "active": false,
   "x": 2268.0,
   "y": 334.0,
   "z": -2584.1,
   "grid_w": 1,
   "grid_h": 1,
   "cell_size": 3.0,
   "world_w": 3.0,
   "world_h": 3.0,
   "resources_current": 0,
   "resources_max": 0
  },
  {
   "idx": 101,
   "name": "ResourceArea_Biotics_TarPit",
   "type": "Biotics",
   "active": false,
   "x": -2254.3,
   "y": 151.3,
   "z": -456.6,
   "grid_w": 1,
   "grid_h": 1,
   "cell_size": 3.0,
   "world_w": 3.0,
   "world_h": 3.0,
   "resources_current": 0,
   "resources_max": 0
  },
  {
   "idx": 102,
   "name": "ResourceArea_Biotics_TarPit",
   "type": "Biotics",
   "active": false,
   "x": -1897.1,
   "y": 283.4,
   "z": 2416.2,
   "grid_w": 1,
   "grid_h": 1,
   "cell_size": 3.0,
   "world_w": 3.0,
   "world_h": 3.0,
   "resources_current": 0,
   "resources_max": 0
  },
  {
   "idx": 103,
   "name": "ResourceArea_Biotics_TarPit",
   "type": "Biotics",
   "active": false,
   "x": 1670.8,
   "y": 288.7,
   "z": -1984.7,
   "grid_w": 1,
   "grid_h": 1,
   "cell_size": 3.0,
   "world_w": 3.0,
   "world_h": 3.0,
   "resources_current": 0,
   "resources_max": 0
  },
  {
   "idx": 104,
   "name": "ResourceArea_Biotics_TarPit",
   "type": "Biotics",
   "active": false,
   "x": -1700.1,
   "y": 52.1,
   "z": -934.3,
   "grid_w": 1,
   "grid_h": 1,
   "cell_size": 3.0,
   "world_w": 3.0,
   "world_h": 3.0,
   "resources_current": 0,
   "resources_max": 0
  },
  {
   "idx": 105,
   "name": "ResourceArea_Biotics_TarPit",
   "type": "Biotics",
   "active": false,
   "x": 2209.3,
   "y": 381.5,
   "z": 348.4,
   "grid_w": 1,
   "grid_h": 1,
   "cell_size": 3.0,
   "world_w": 3.0,
   "world_h": 3.0,
   "resources_current": 0,
   "resources_max": 0
  },
  {
   "idx": 106,
   "name": "ResourceArea_Biotics_TarPit",
   "type": "Biotics",
   "active": false,
   "x": 1635.2,
   "y": 445.4,
   "z": 2772.9,
   "grid_w": 1,
   "grid_h": 1,
   "cell_size": 3.0,
   "world_w": 3.0,
   "world_h": 3.0,
   "resources_current": 0,
   "resources_max": 0
  },
  {
   "idx": 107,
   "name": "ResourceArea_Biotics_TarPit",
   "type": "Biotics",
   "active": false,
   "x": 2591.2,
   "y": 370.9,
   "z": -1510.7,
   "grid_w": 1,
   "grid_h": 1,
   "cell_size": 3.0,
   "world_w": 3.0,
   "world_h": 3.0,
   "resources_current": 0,
   "resources_max": 0
  },
  {
   "idx": 108,
   "name": "ResourceArea_Biotics_TarPit",
   "type": "Biotics",
   "active": false,
   "x": 1744.3,
   "y": 451.6,
   "z": 1478.1,
   "grid_w": 1,
   "grid_h": 1,
   "cell_size": 3.0,
   "world_w": 3.0,
   "world_h": 3.0,
   "resources_current": 0,
   "resources_max": 0
  },
  {
   "idx": 109,
   "name": "ResourceArea_Biotics_TarPit",
   "type": "Biotics",
   "active": false,
   "x": -1114.3,
   "y": 166.7,
   "z": -64.9,
   "grid_w": 1,
   "grid_h": 1,
   "cell_size": 3.0,
   "world_w": 3.0,
   "world_h": 3.0,
   "resources_current": 0,
   "resources_max": 0
  },
  {
   "idx": 110,
   "name": "ResourceArea_Biotics_TarPit",
   "type": "Biotics",
   "active": false,
   "x": 2650.4,
   "y": 456.8,
   "z": 2113.4,
   "grid_w": 1,
   "grid_h": 1,
   "cell_size": 3.0,
   "world_w": 3.0,
   "world_h": 3.0,
   "resources_current": 0,
   "resources_max": 0
  },
  {
   "idx": 111,
   "name": "ResourceArea_Biotics_TarPit",
   "type": "Biotics",
   "active": false,
   "x": 2392.4,
   "y": 472.1,
   "z": 1449.3,
   "grid_w": 1,
   "grid_h": 1,
   "cell_size": 3.0,
   "world_w": 3.0,
   "world_h": 3.0,
   "resources_current": 0,
   "resources_max": 0
  },
  {
   "idx": 112,
   "name": "ResourceArea_Biotics_TarPit",
   "type": "Biotics",
   "active": false,
   "x": -2706.4,
   "y": 214.4,
   "z": -2408.4,
   "grid_w": 1,
   "grid_h": 1,
   "cell_size": 3.0,
   "world_w": 3.0,
   "world_h": 3.0,
   "resources_current": 0,
   "resources_max": 0
  },
  {
   "idx": 113,
   "name": "ResourceArea_Biotics_TarPit",
   "type": "Biotics",
   "active": false,
   "x": -1117.6,
   "y": 219.7,
   "z": -2576.0,
   "grid_w": 1,
   "grid_h": 1,
   "cell_size": 3.0,
   "world_w": 3.0,
   "world_h": 3.0,
   "resources_current": 0,
   "resources_max": 0
  },
  {
   "idx": 114,
   "name": "ResourceArea_Biotics_TarPit",
   "type": "Biotics",
   "active": false,
   "x": -1162.0,
   "y": 280.4,
   "z": 2085.3,
   "grid_w": 1,
   "grid_h": 1,
   "cell_size": 3.0,
   "world_w": 3.0,
   "world_h": 3.0,
   "resources_current": 0,
   "resources_max": 0
  },
  {
   "idx": 115,
   "name": "ResourceArea_Biotics_TarPit",
   "type": "Biotics",
   "active": false,
   "x": 1092.4,
   "y": 381.3,
   "z": 2004.5,
   "grid_w": 1,
   "grid_h": 1,
   "cell_size": 3.0,
   "world_w": 3.0,
   "world_h": 3.0,
   "resources_current": 0,
   "resources_max": 0
  },
  {
   "idx": 116,
   "name": "ResourceArea_Biotics_TarPit",
   "type": "Biotics",
   "active": false,
   "x": -2583.5,
   "y": 113.2,
   "z": -1548.0,
   "grid_w": 1,
   "grid_h": 1,
   "cell_size": 3.0,
   "world_w": 3.0,
   "world_h": 3.0,
   "resources_current": 0,
   "resources_max": 0
  },
  {
   "idx": 117,
   "name": "ResourceArea_Biotics_TarPit",
   "type": "Biotics",
   "active": false,
   "x": -945.2,
   "y": 217.6,
   "z": 1428.9,
   "grid_w": 1,
   "grid_h": 1,
   "cell_size": 3.0,
   "world_w": 3.0,
   "world_h": 3.0,
   "resources_current": 0,
   "resources_max": 0
  },
  {
   "idx": 118,
   "name": "ResourceArea_Biotics_TarPit",
   "type": "Biotics",
   "active": false,
   "x": 867.7,
   "y": 46.3,
   "z": -1017.1,
   "grid_w": 1,
   "grid_h": 1,
   "cell_size": 3.0,
   "world_w": 3.0,
   "world_h": 3.0,
   "resources_current": 0,
   "resources_max": 0
  },
  {
   "idx": 119,
   "name": "ResourceArea_Biotics_TarPit",
   "type": "Biotics",
   "active": false,
   "x": -2491.9,
   "y": 207.9,
   "z": 389.8,
   "grid_w": 1,
   "grid_h": 1,
   "cell_size": 3.0,
   "world_w": 3.0,
   "world_h": 3.0,
   "resources_current": 0,
   "resources_max": 0
  },
  {
   "idx": 120,
   "name": "ResourceArea_Biotics_TarPit",
   "type": "Biotics",
   "active": false,
   "x": -2834.1,
   "y": 250.6,
   "z": 1731.8,
   "grid_w": 1,
   "grid_h": 1,
   "cell_size": 3.0,
   "world_w": 3.0,
   "world_h": 3.0,
   "resources_current": 0,
   "resources_max": 0
  },
  {
   "idx": 121,
   "name": "ResourceArea_Biotics_TarPit",
   "type": "Biotics",
   "active": false,
   "x": 385.8,
   "y": 138.8,
   "z": 2039.0,
   "grid_w": 1,
   "grid_h": 1,
   "cell_size": 3.0,
   "world_w": 3.0,
   "world_h": 3.0,
   "resources_current": 0,
   "resources_max": 0
  },
  {
   "idx": 122,
   "name": "ResourceArea_Biotics_TarPit",
   "type": "Biotics",
   "active": false,
   "x": -2023.9,
   "y": 222.1,
   "z": -2260.5,
   "grid_w": 1,
   "grid_h": 1,
   "cell_size": 3.0,
   "world_w": 3.0,
   "world_h": 3.0,
   "resources_current": 0,
   "resources_max": 0
  },
  {
   "idx": 123,
   "name": "ResourceArea_Biotics_TarPit",
   "type": "Biotics",
   "active": false,
   "x": -1815.0,
   "y": 240.6,
   "z": 1068.3,
   "grid_w": 1,
   "grid_h": 1,
   "cell_size": 3.0,
   "world_w": 3.0,
   "world_h": 3.0,
   "resources_current": 0,
   "resources_max": 0
  },
  {
   "idx": 124,
   "name": "ResourceArea_Biotics_TarPit",
   "type": "Biotics",
   "active": false,
   "x": 1886.7,
   "y": 328.4,
   "z": -538.9,
   "grid_w": 1,
   "grid_h": 1,
   "cell_size": 3.0,
   "world_w": 3.0,
   "world_h": 3.0,
   "resources_current": 0,
   "resources_max": 0
  },
  {
   "idx": 125,
   "name": "ResourceArea_Biotics_TarPit",
   "type": "Biotics",
   "active": false,
   "x": 1065.2,
   "y": 56.2,
   "z": -237.7,
   "grid_w": 1,
   "grid_h": 1,
   "cell_size": 3.0,
   "world_w": 3.0,
   "world_h": 3.0,
   "resources_current": 0,
   "resources_max": 0
  },
  {
   "idx": 126,
   "name": "ResourceArea_Biotics_TarPit",
   "type": "Biotics",
   "active": false,
   "x": -831.6,
   "y": 173.1,
   "z": 2931.5,
   "grid_w": 1,
   "grid_h": 1,
   "cell_size": 3.0,
   "world_w": 3.0,
   "world_h": 3.0,
   "resources_current": 0,
   "resources_max": 0
  },
  {
   "idx": 127,
   "name": "ResourceArea_Biotics_TarPit",
   "type": "Biotics",
   "active": false,
   "x": -1260.3,
   "y": 31.3,
   "z": -1349.5,
   "grid_w": 1,
   "grid_h": 1,
   "cell_size": 3.0,
   "world_w": 3.0,
   "world_h": 3.0,
   "resources_current": 0,
   "resources_max": 0
  },
  {
   "idx": 128,
   "name": "ResourceArea_Biotics_TarPit",
   "type": "Biotics",
   "active": false,
   "x": -267.7,
   "y": 39.5,
   "z": -339.7,
   "grid_w": 1,
   "grid_h": 1,
   "cell_size": 3.0,
   "world_w": 3.0,
   "world_h": 3.0,
   "resources_current": 0,
   "resources_max": 0
  },
  {
   "idx": 129,
   "name": "ResourceArea_Biotics_TarPit",
   "type": "Biotics",
   "active": false,
   "x": 895.2,
   "y": 355.6,
   "z": 2343.7,
   "grid_w": 1,
   "grid_h": 1,
   "cell_size": 3.0,
   "world_w": 3.0,
   "world_h": 3.0,
   "resources_current": 0,
   "resources_max": 0
  },
  {
   "idx": 130,
   "name": "ResourceArea_Biotics_TarPit",
   "type": "Biotics",
   "active": false,
   "x": 1139.5,
   "y": 49.7,
   "z": -1451.0,
   "grid_w": 1,
   "grid_h": 1,
   "cell_size": 3.0,
   "world_w": 3.0,
   "world_h": 3.0,
   "resources_current": 0,
   "resources_max": 0
  },
  {
   "idx": 131,
   "name": "ResourceArea_Biotics_TarPit",
   "type": "Biotics",
   "active": false,
   "x": 2661.5,
   "y": 479.5,
   "z": 1114.5,
   "grid_w": 1,
   "grid_h": 1,
   "cell_size": 3.0,
   "world_w": 3.0,
   "world_h": 3.0,
   "resources_current": 0,
   "resources_max": 0
  },
  {
   "idx": 132,
   "name": "ResourceArea_Biotics_TarPit",
   "type": "Biotics",
   "active": false,
   "x": -2945.2,
   "y": 71.6,
   "z": -1351.7,
   "grid_w": 1,
   "grid_h": 1,
   "cell_size": 3.0,
   "world_w": 3.0,
   "world_h": 3.0,
   "resources_current": 0,
   "resources_max": 0
  },
  {
   "idx": 133,
   "name": "ResourceArea_Biotics_TarPit",
   "type": "Biotics",
   "active": false,
   "x": 256.4,
   "y": 39.9,
   "z": -1257.8,
   "grid_w": 1,
   "grid_h": 1,
   "cell_size": 3.0,
   "world_w": 3.0,
   "world_h": 3.0,
   "resources_current": 0,
   "resources_max": 0
  },
  {
   "idx": 134,
   "name": "ResourceArea_Biotics_TarPit",
   "type": "Biotics",
   "active": false,
   "x": -1178.8,
   "y": 219.0,
   "z": 681.7,
   "grid_w": 1,
   "grid_h": 1,
   "cell_size": 3.0,
   "world_w": 3.0,
   "world_h": 3.0,
   "resources_current": 0,
   "resources_max": 0
  },
  {
   "idx": 135,
   "name": "ResourceArea_Biotics_TarPit",
   "type": "Biotics",
   "active": false,
   "x": 2220.7,
   "y": 349.0,
   "z": -1873.7,
   "grid_w": 1,
   "grid_h": 1,
   "cell_size": 3.0,
   "world_w": 3.0,
   "world_h": 3.0,
   "resources_current": 0,
   "resources_max": 0
  },
  {
   "idx": 136,
   "name": "ResourceArea_Biotics_TarPit",
   "type": "Biotics",
   "active": false,
   "x": -667.1,
   "y": 32.1,
   "z": -484.9,
   "grid_w": 1,
   "grid_h": 1,
   "cell_size": 3.0,
   "world_w": 3.0,
   "world_h": 3.0,
   "resources_current": 0,
   "resources_max": 0
  },
  {
   "idx": 137,
   "name": "ResourceArea_Biotics_TarPit",
   "type": "Biotics",
   "active": false,
   "x": 1611.0,
   "y": 346.4,
   "z": 234.8,
   "grid_w": 1,
   "grid_h": 1,
   "cell_size": 3.0,
   "world_w": 3.0,
   "world_h": 3.0,
   "resources_current": 0,
   "resources_max": 0
  },
  {
   "idx": 138,
   "name": "ResourceArea_Biotics_TarPit",
   "type": "Biotics",
   "active": false,
   "x": 1355.7,
   "y": 422.1,
   "z": 1589.2,
   "grid_w": 1,
   "grid_h": 1,
   "cell_size": 3.0,
   "world_w": 3.0,
   "world_h": 3.0,
   "resources_current": 0,
   "resources_max": 0
  },
  {
   "idx": 139,
   "name": "ResourceArea_Biotics_TarPit",
   "type": "Biotics",
   "active": false,
   "x": -2771.8,
   "y": 215.6,
   "z": 1136.2,
   "grid_w": 1,
   "grid_h": 1,
   "cell_size": 3.0,
   "world_w": 3.0,
   "world_h": 3.0,
   "resources_current": 0,
   "resources_max": 0
  },
  {
   "idx": 140,
   "name": "ResourceArea_Biotics_TarPit",
   "type": "Biotics",
   "active": false,
   "x": 266.1,
   "y": 32.8,
   "z": -230.7,
   "grid_w": 1,
   "grid_h": 1,
   "cell_size": 3.0,
   "world_w": 3.0,
   "world_h": 3.0,
   "resources_current": 0,
   "resources_max": 0
  },
  {
   "idx": 141,
   "name": "ResourceArea_Biotics_TarPit",
   "type": "Biotics",
   "active": false,
   "x": -2006.3,
   "y": 258.9,
   "z": 2025.0,
   "grid_w": 1,
   "grid_h": 1,
   "cell_size": 3.0,
   "world_w": 3.0,
   "world_h": 3.0,
   "resources_current": 0,
   "resources_max": 0
  },
  {
   "idx": 142,
   "name": "ResourceArea_Biotics_TarPit",
   "type": "Biotics",
   "active": false,
   "x": -2524.2,
   "y": 198.2,
   "z": -2619.0,
   "grid_w": 1,
   "grid_h": 1,
   "cell_size": 3.0,
   "world_w": 3.0,
   "world_h": 3.0,
   "resources_current": 0,
   "resources_max": 0
  },
  {
   "idx": 143,
   "name": "ResourceArea_Biotics_TarPit",
   "type": "Biotics",
   "active": false,
   "x": 2236.0,
   "y": 461.1,
   "z": 1895.4,
   "grid_w": 1,
   "grid_h": 1,
   "cell_size": 3.0,
   "world_w": 3.0,
   "world_h": 3.0,
   "resources_current": 0,
   "resources_max": 0
  },
  {
   "idx": 144,
   "name": "ResourceArea_Biotics_TarPit",
   "type": "Biotics",
   "active": false,
   "x": 587.7,
   "y": 51.6,
   "z": 1419.3,
   "grid_w": 1,
   "grid_h": 1,
   "cell_size": 3.0,
   "world_w": 3.0,
   "world_h": 3.0,
   "resources_current": 0,
   "resources_max": 0
  },
  {
   "idx": 145,
   "name": "ResourceArea_Biotics_TarPit",
   "type": "Biotics",
   "active": false,
   "x": 1360.8,
   "y": 243.2,
   "z": -2070.3,
   "grid_w": 1,
   "grid_h": 1,
   "cell_size": 3.0,
   "world_w": 3.0,
   "world_h": 3.0,
   "resources_current": 0,
   "resources_max": 0
  },
  {
   "idx": 146,
   "name": "ResourceArea_Biotics_TarPit",
   "type": "Biotics",
   "active": false,
   "x": -1426.0,
   "y": 208.6,
   "z": -1911.1,
   "grid_w": 1,
   "grid_h": 1,
   "cell_size": 3.0,
   "world_w": 3.0,
   "world_h": 3.0,
   "resources_current": 0,
   "resources_max": 0
  },
  {
   "idx": 147,
   "name": "ResourceArea_Biotics_TarPit",
   "type": "Biotics",
   "active": false,
   "x": -2244.8,
   "y": 192.7,
   "z": -1869.9,
   "grid_w": 1,
   "grid_h": 1,
   "cell_size": 3.0,
   "world_w": 3.0,
   "world_h": 3.0,
   "resources_current": 0,
   "resources_max": 0
  },
  {
   "idx": 148,
   "name": "ResourceArea_Biotics_TarPit",
   "type": "Biotics",
   "active": false,
   "x": 2954.0,
   "y": 378.6,
   "z": -1082.2,
   "grid_w": 1,
   "grid_h": 1,
   "cell_size": 3.0,
   "world_w": 3.0,
   "world_h": 3.0,
   "resources_current": 0,
   "resources_max": 0
  },
  {
   "idx": 149,
   "name": "ResourceArea_Biotics_TarPit",
   "type": "Biotics",
   "active": false,
   "x": -597.6,
   "y": 167.3,
   "z": 2071.3,
   "grid_w": 1,
   "grid_h": 1,
   "cell_size": 3.0,
   "world_w": 3.0,
   "world_h": 3.0,
   "resources_current": 0,
   "resources_max": 0
  },
  {
   "idx": 150,
   "name": "ResourceArea_Biotics_TarPit",
   "type": "Biotics",
   "active": false,
   "x": -302.1,
   "y": 81.7,
   "z": 2953.4,
   "grid_w": 1,
   "grid_h": 1,
   "cell_size": 3.0,
   "world_w": 3.0,
   "world_h": 3.0,
   "resources_current": 0,
   "resources_max": 0
  },
  {
   "idx": 151,
   "name": "ResourceArea_Biotics_TarPit",
   "type": "Biotics",
   "active": false,
   "x": -1689.9,
   "y": 239.3,
   "z": 1410.6,
   "grid_w": 1,
   "grid_h": 1,
   "cell_size": 3.0,
   "world_w": 3.0,
   "world_h": 3.0,
   "resources_current": 0,
   "resources_max": 0
  },
  {
   "idx": 152,
   "name": "ResourceArea_Biotics_TarPit",
   "type": "Biotics",
   "active": false,
   "x": 2306.8,
   "y": 410.1,
   "z": 713.5,
   "grid_w": 1,
   "grid_h": 1,
   "cell_size": 3.0,
   "world_w": 3.0,
   "world_h": 3.0,
   "resources_current": 0,
   "resources_max": 0
  },
  {
   "idx": 153,
   "name": "ResourceArea_Biotics_TarPit",
   "type": "Biotics",
   "active": false,
   "x": 2614.0,
   "y": 380.5,
   "z": -2217.6,
   "grid_w": 1,
   "grid_h": 1,
   "cell_size": 3.0,
   "world_w": 3.0,
   "world_h": 3.0,
   "resources_current": 0,
   "resources_max": 0
  },
  {
   "idx": 154,
   "name": "ResourceArea_Biotics_TarPit",
   "type": "Biotics",
   "active": false,
   "x": -379.3,
   "y": 178.2,
   "z": -2153.9,
   "grid_w": 1,
   "grid_h": 1,
   "cell_size": 3.0,
   "world_w": 3.0,
   "world_h": 3.0,
   "resources_current": 0,
   "resources_max": 0
  },
  {
   "idx": 155,
   "name": "ResourceArea_Biotics_TarPit",
   "type": "Biotics",
   "active": false,
   "x": -1153.8,
   "y": 35.5,
   "z": -658.7,
   "grid_w": 1,
   "grid_h": 1,
   "cell_size": 3.0,
   "world_w": 3.0,
   "world_h": 3.0,
   "resources_current": 0,
   "resources_max": 0
  },
  {
   "idx": 156,
   "name": "ResourceArea_Biotics_TarPit",
   "type": "Biotics",
   "active": false,
   "x": -782.5,
   "y": 200.3,
   "z": -2985.9,
   "grid_w": 1,
   "grid_h": 1,
   "cell_size": 3.0,
   "world_w": 3.0,
   "world_h": 3.0,
   "resources_current": 0,
   "resources_max": 0
  },
  {
   "idx": 157,
   "name": "ResourceArea_Biotics_TarPit",
   "type": "Biotics",
   "active": false,
   "x": -2481.5,
   "y": 63.7,
   "z": -890.1,
   "grid_w": 1,
   "grid_h": 1,
   "cell_size": 3.0,
   "world_w": 3.0,
   "world_h": 3.0,
   "resources_current": 0,
   "resources_max": 0
  },
  {
   "idx": 158,
   "name": "ResourceArea_Biotics_TarPit",
   "type": "Biotics",
   "active": false,
   "x": 1257.8,
   "y": 311.5,
   "z": 854.1,
   "grid_w": 1,
   "grid_h": 1,
   "cell_size": 3.0,
   "world_w": 3.0,
   "world_h": 3.0,
   "resources_current": 0,
   "resources_max": 0
  },
  {
   "idx": 159,
   "name": "ResourceArea_Biotics_TarPit",
   "type": "Biotics",
   "active": false,
   "x": 2268.5,
   "y": 464.0,
   "z": 2635.0,
   "grid_w": 1,
   "grid_h": 1,
   "cell_size": 3.0,
   "world_w": 3.0,
   "world_h": 3.0,
   "resources_current": 0,
   "resources_max": 0
  },
  {
   "idx": 160,
   "name": "ResourceArea_Biotics_TarPit",
   "type": "Biotics",
   "active": false,
   "x": 2198.9,
   "y": 386.3,
   "z": -331.3,
   "grid_w": 1,
   "grid_h": 1,
   "cell_size": 3.0,
   "world_w": 3.0,
   "world_h": 3.0,
   "resources_current": 0,
   "resources_max": 0
  },
  {
   "idx": 161,
   "name": "ResourceArea_Biotics_TarPit",
   "type": "Biotics",
   "active": false,
   "x": -514.7,
   "y": 42.0,
   "z": -1276.9,
   "grid_w": 1,
   "grid_h": 1,
   "cell_size": 3.0,
   "world_w": 3.0,
   "world_h": 3.0,
   "resources_current": 0,
   "resources_max": 0
  },
  {
   "idx": 162,
   "name": "ResourceArea_Biotics_TarPit",
   "type": "Biotics",
   "active": false,
   "x": 341.3,
   "y": 178.1,
   "z": 2633.7,
   "grid_w": 1,
   "grid_h": 1,
   "cell_size": 3.0,
   "world_w": 3.0,
   "world_h": 3.0,
   "resources_current": 0,
   "resources_max": 0
  },
  {
   "idx": 163,
   "name": "ResourceArea_Biotics_TarPit",
   "type": "Biotics",
   "active": false,
   "x": -1935.1,
   "y": 266.2,
   "z": 611.9,
   "grid_w": 1,
   "grid_h": 1,
   "cell_size": 3.0,
   "world_w": 3.0,
   "world_h": 3.0,
   "resources_current": 0,
   "resources_max": 0
  },
  {
   "idx": 164,
   "name": "ResourceArea_Biotics_TarPit",
   "type": "Biotics",
   "active": false,
   "x": -2127.5,
   "y": 29.4,
   "z": -1303.1,
   "grid_w": 1,
   "grid_h": 1,
   "cell_size": 3.0,
   "world_w": 3.0,
   "world_h": 3.0,
   "resources_current": 0,
   "resources_max": 0
  },
  {
   "idx": 165,
   "name": "ResourceArea_Biotics_TarPit",
   "type": "Biotics",
   "active": false,
   "x": -1938.0,
   "y": 194.8,
   "z": -33.7,
   "grid_w": 1,
   "grid_h": 1,
   "cell_size": 3.0,
   "world_w": 3.0,
   "world_h": 3.0,
   "resources_current": 0,
   "resources_max": 0
  },
  {
   "idx": 166,
   "name": "ResourceArea_Biotics_TarPit",
   "type": "Biotics",
   "active": false,
   "x": 1651.8,
   "y": 358.4,
   "z": 904.5,
   "grid_w": 1,
   "grid_h": 1,
   "cell_size": 3.0,
   "world_w": 3.0,
   "world_h": 3.0,
   "resources_current": 0,
   "resources_max": 0
  },
  {
   "idx": 167,
   "name": "ResourceArea_Biotics_TarPit",
   "type": "Biotics",
   "active": false,
   "x": -2273.7,
   "y": 257.3,
   "z": 1649.4,
   "grid_w": 1,
   "grid_h": 1,
   "cell_size": 3.0,
   "world_w": 3.0,
   "world_h": 3.0,
   "resources_current": 0,
   "resources_max": 0
  },
  {
   "idx": 168,
   "name": "ResourceArea_Biotics_TarPit",
   "type": "Biotics",
   "active": false,
   "x": 1070.5,
   "y": 300.5,
   "z": 2752.5,
   "grid_w": 1,
   "grid_h": 1,
   "cell_size": 3.0,
   "world_w": 3.0,
   "world_h": 3.0,
   "resources_current": 0,
   "resources_max": 0
  },
  {
   "idx": 169,
   "name": "ResourceArea_Biotics_TarPit",
   "type": "Biotics",
   "active": false,
   "x": -2818.8,
   "y": 278.6,
   "z": 2782.8,
   "grid_w": 1,
   "grid_h": 1,
   "cell_size": 3.0,
   "world_w": 3.0,
   "world_h": 3.0,
   "resources_current": 0,
   "resources_max": 0
  },
  {
   "idx": 170,
   "name": "ResourceArea_Biotics_TarPit",
   "type": "Biotics",
   "active": false,
   "x": 2216.4,
   "y": 335.5,
   "z": -879.3,
   "grid_w": 1,
   "grid_h": 1,
   "cell_size": 3.0,
   "world_w": 3.0,
   "world_h": 3.0,
   "resources_current": 0,
   "resources_max": 0
  },
  {
   "idx": 171,
   "name": "ResourceArea_Biotics_TarPit",
   "type": "Biotics",
   "active": false,
   "x": -149.0,
   "y": 43.4,
   "z": 725.6,
   "grid_w": 1,
   "grid_h": 1,
   "cell_size": 3.0,
   "world_w": 3.0,
   "world_h": 3.0,
   "resources_current": 0,
   "resources_max": 0
  },
  {
   "idx": 172,
   "name": "ResourceArea_Biotics_TarPit",
   "type": "Biotics",
   "active": false,
   "x": 294.0,
   "y": 33.6,
   "z": 471.7,
   "grid_w": 1,
   "grid_h": 1,
   "cell_size": 3.0,
   "world_w": 3.0,
   "world_h": 3.0,
   "resources_current": 0,
   "resources_max": 0
  },
  {
   "idx": 173,
   "name": "ResourceArea_Biotics_TarPit",
   "type": "Biotics",
   "active": false,
   "x": -720.7,
   "y": 22.5,
   "z": 199.1,
   "grid_w": 1,
   "grid_h": 1,
   "cell_size": 3.0,
   "world_w": 3.0,
   "world_h": 3.0,
   "resources_current": 0,
   "resources_max": 0
  },
  {
   "idx": 174,
   "name": "ResourceArea_Biotics_TarPit",
   "type": "Biotics",
   "active": false,
   "x": 1205.6,
   "y": 44.0,
   "z": -692.6,
   "grid_w": 1,
   "grid_h": 1,
   "cell_size": 3.0,
   "world_w": 3.0,
   "world_h": 3.0,
   "resources_current": 0,
   "resources_max": 0
  },
  {
   "idx": 175,
   "name": "ResourceArea_Biotics_TarPit",
   "type": "Biotics",
   "active": false,
   "x": 320.7,
   "y": 86.1,
   "z": -2764.9,
   "grid_w": 1,
   "grid_h": 1,
   "cell_size": 3.0,
   "world_w": 3.0,
   "world_h": 3.0,
   "resources_current": 0,
   "resources_max": 0
  }
 ]
}